<string id="ogg_flash_inv_1">
    <rus>Музыкальная флеш-карта от Сидоровича.</rus>
</string>
<string id="flash_1_track_1">
	<rus>Andy Panda/Pastor Napas – 14</rus>
</string>	
<string id="flash_1_track_2">
	<rus>Andy Panda/Змей – 4 U</rus>
</string>	
<string id="flash_1_track_3">
	<rus>Andy Panda/Miyagi – Endorphin</rus>
</string>	
<string id="flash_1_track_4">
	<rus>Andy Panda/Castle – I Wanna Feel the Love</rus>
</string>	
<string id="flash_1_track_5">
	<rus>Andy Panda/Miyagi/TumaniYO – Jumanji</rus>
</string>	

<string id="ogg_flash_inv_2">
    <rus>Музыкальная флеш-карта от Бармена.</rus>
</string>
<string id="flash_2_track_1">
	<rus>Andy Panda – King Kong</rus>
</string>	
<string id="flash_2_track_2">
	<rus>Andy Panda – Mama Africa</rus>
</string>	
<string id="flash_2_track_3">
	<rus>Andy Panda – Orange Sunset</rus>
</string>	
<string id="flash_2_track_4">
	<rus>Andy Panda – Rude Mantras</rus>
</string>	
<string id="flash_2_track_5">
	<rus>Andy Panda/TumaniYO/Niman – Sun</rus>
</string>	
<string id="flash_2_track_6">
	<rus>DIPIENS – Perfectly</rus>
</string>	
<string id="flash_2_track_7">
	<rus>Disturbed – Decadence</rus>
</string>	
<string id="flash_2_track_8">
	<rus>Disturbed – Sacred Lie</rus>
</string>	
<string id="flash_2_track_9">
	<rus>Disturbed – Sons of Plunder</rus>
</string>	
<string id="flash_2_track_10">
	<rus>Disturbed – Stricken</rus>
</string>	
<string id="flash_2_track_11">
	<rus>DJ Mix – Dolbit</rus>
</string>	
<string id="flash_2_track_12">
	<rus>DMXS – Dead Space</rus>
</string>	

